devnet/__init__.py
devnet/config.py
devnet/trainer.py
devnet-0.1.0.dist-info/LICENSE
devnet-0.1.0.dist-info/WHEEL
devnet-0.1.0.dist-info/METADATA
devnet-0.1.0.dist-info/RECORD
